setup.py
nj_distributions/Binomialdistribution.py
nj_distributions/Gaussiandistribution.py
nj_distributions/Generaldistribution.py
nj_distributions/__init__.py
nj_distributions.egg-info/PKG-INFO
nj_distributions.egg-info/SOURCES.txt
nj_distributions.egg-info/dependency_links.txt
nj_distributions.egg-info/not-zip-safe
nj_distributions.egg-info/top_level.txt