Metadata-Version: 1.0
Name: nj-distributions
Version: 0.1
Summary: Gaussian distributions and Binomial distributions
Home-page: UNKNOWN
Author: Nikita Jain
Author-email: jnikita356@gmail.com
License: UNKNOWN
Platform: UNKNOWN
